{
  "_meta": {
    "name": {
      "zh": "文件操作",
      "en": "File Operations"
    },
    "source": "builtin"
  },
  "commands": [
    {
      "id": "find-file-mac",
      "name": {
        "zh": "按名称查找文件",
        "en": "Find Files by Name"
      },
      "tags": [
        "文件",
        "file",
        "查找",
        "find"
      ],
      "category": "file",
      "platform": "mac",
      "exec": {
        "program": "find",
        "args": [
          "{{path}}",
          "-name"
        ],
        "stdinArgKey": "pattern"
      },
      "adminRequired": false,
      "args": [
        {
          "key": "path",
          "type": "path",
          "required": true,
          "default": ".",
          "label": {
            "zh": "path",
            "en": "Path"
          }
        },
        {
          "key": "pattern",
          "type": "text",
          "required": true,
          "label": {
            "zh": "pattern",
            "en": "Pattern"
          }
        }
      ]
    },
    {
      "id": "find-file-linux",
      "name": {
        "zh": "按名称查找文件",
        "en": "Find Files by Name"
      },
      "tags": [
        "文件",
        "file",
        "查找",
        "find"
      ],
      "category": "file",
      "platform": "linux",
      "exec": {
        "program": "find",
        "args": [
          "{{path}}",
          "-name"
        ],
        "stdinArgKey": "pattern"
      },
      "adminRequired": false,
      "args": [
        {
          "key": "path",
          "type": "path",
          "required": true,
          "default": ".",
          "label": {
            "zh": "path",
            "en": "Path"
          }
        },
        {
          "key": "pattern",
          "type": "text",
          "required": true,
          "label": {
            "zh": "pattern",
            "en": "Pattern"
          }
        }
      ]
    },
    {
      "id": "find-file-win",
      "name": {
        "zh": "按名称查找文件",
        "en": "Find Files by Name"
      },
      "tags": [
        "文件",
        "file",
        "查找",
        "find"
      ],
      "category": "file",
      "platform": "win",
      "script": {
        "runner": "powershell",
        "command": "Get-ChildItem -Recurse -Filter \"{{pattern}}\" {{path}}"
      },
      "adminRequired": false,
      "args": [
        {
          "key": "path",
          "type": "path",
          "required": true,
          "default": ".",
          "label": {
            "zh": "path",
            "en": "Path"
          }
        },
        {
          "key": "pattern",
          "type": "text",
          "required": true,
          "label": {
            "zh": "pattern",
            "en": "Pattern"
          }
        }
      ],
      "prerequisites": [
        {
          "id": "powershell",
          "type": "shell",
          "required": true,
          "check": "shell:powershell"
        }
      ]
    },
    {
      "id": "find-content-mac",
      "name": {
        "zh": "按内容搜索文件",
        "en": "Search Files by Content"
      },
      "tags": [
        "文件",
        "file",
        "查找",
        "find",
        "内容",
        "content"
      ],
      "category": "file",
      "platform": "mac",
      "exec": {
        "program": "grep",
        "args": [
          "-rn",
          "{{path}}"
        ],
        "stdinArgKey": "pattern"
      },
      "adminRequired": false,
      "args": [
        {
          "key": "pattern",
          "type": "text",
          "required": true,
          "label": {
            "zh": "pattern",
            "en": "Pattern"
          }
        },
        {
          "key": "path",
          "type": "path",
          "required": true,
          "default": ".",
          "label": {
            "zh": "path",
            "en": "Path"
          }
        }
      ]
    },
    {
      "id": "find-content-linux",
      "name": {
        "zh": "按内容搜索文件",
        "en": "Search Files by Content"
      },
      "tags": [
        "文件",
        "file",
        "查找",
        "find",
        "内容",
        "content"
      ],
      "category": "file",
      "platform": "linux",
      "exec": {
        "program": "grep",
        "args": [
          "-rn",
          "{{path}}"
        ],
        "stdinArgKey": "pattern"
      },
      "adminRequired": false,
      "args": [
        {
          "key": "pattern",
          "type": "text",
          "required": true,
          "label": {
            "zh": "pattern",
            "en": "Pattern"
          }
        },
        {
          "key": "path",
          "type": "path",
          "required": true,
          "default": ".",
          "label": {
            "zh": "path",
            "en": "Path"
          }
        }
      ]
    },
    {
      "id": "find-content-win",
      "name": {
        "zh": "按内容搜索文件",
        "en": "Search Files by Content"
      },
      "tags": [
        "文件",
        "file",
        "查找",
        "find",
        "内容",
        "content"
      ],
      "category": "file",
      "platform": "win",
      "script": {
        "runner": "powershell",
        "command": "Select-String -Recurse -Pattern \"{{pattern}}\" -Path \"{{path}}\""
      },
      "adminRequired": false,
      "args": [
        {
          "key": "pattern",
          "type": "text",
          "required": true,
          "label": {
            "zh": "pattern",
            "en": "Pattern"
          }
        },
        {
          "key": "path",
          "type": "path",
          "required": true,
          "default": ".",
          "label": {
            "zh": "path",
            "en": "Path"
          }
        }
      ],
      "prerequisites": [
        {
          "id": "powershell",
          "type": "shell",
          "required": true,
          "check": "shell:powershell"
        }
      ]
    },
    {
      "id": "list-files-mac",
      "name": {
        "zh": "列出目录内容",
        "en": "List Directory Contents"
      },
      "tags": [
        "文件",
        "file",
        "列表",
        "list",
        "files",
        "目录",
        "directory"
      ],
      "category": "file",
      "platform": "mac",
      "exec": {
        "program": "ls",
        "args": [
          "-la",
          "{{path}}"
        ]
      },
      "adminRequired": false,
      "args": [
        {
          "key": "path",
          "type": "path",
          "required": true,
          "default": ".",
          "label": {
            "zh": "path",
            "en": "Path"
          }
        }
      ]
    },
    {
      "id": "list-files-linux",
      "name": {
        "zh": "列出目录内容",
        "en": "List Directory Contents"
      },
      "tags": [
        "文件",
        "file",
        "列表",
        "list",
        "files",
        "目录",
        "directory"
      ],
      "category": "file",
      "platform": "linux",
      "exec": {
        "program": "ls",
        "args": [
          "-la",
          "{{path}}"
        ]
      },
      "adminRequired": false,
      "args": [
        {
          "key": "path",
          "type": "path",
          "required": true,
          "default": ".",
          "label": {
            "zh": "path",
            "en": "Path"
          }
        }
      ]
    },
    {
      "id": "list-files-win",
      "name": {
        "zh": "列出目录内容",
        "en": "List Directory Contents"
      },
      "tags": [
        "文件",
        "file",
        "列表",
        "list",
        "files",
        "目录",
        "directory"
      ],
      "category": "file",
      "platform": "win",
      "script": {
        "runner": "powershell",
        "command": "Get-ChildItem -Force {{path}}"
      },
      "adminRequired": false,
      "args": [
        {
          "key": "path",
          "type": "path",
          "required": true,
          "default": ".",
          "label": {
            "zh": "path",
            "en": "Path"
          }
        }
      ],
      "prerequisites": [
        {
          "id": "powershell",
          "type": "shell",
          "required": true,
          "check": "shell:powershell"
        }
      ]
    },
    {
      "id": "tree-mac",
      "name": {
        "zh": "目录树结构",
        "en": "Show Directory Tree"
      },
      "tags": [
        "文件",
        "file",
        "树",
        "tree",
        "目录",
        "directory"
      ],
      "category": "file",
      "platform": "mac",
      "exec": {
        "program": "tree",
        "args": [
          "-L",
          "{{depth}}",
          "{{path}}"
        ]
      },
      "adminRequired": false,
      "args": [
        {
          "key": "path",
          "type": "path",
          "required": true,
          "default": ".",
          "label": {
            "zh": "path",
            "en": "Path"
          }
        },
        {
          "key": "depth",
          "type": "number",
          "required": true,
          "default": "3",
          "validation": {
            "min": 1,
            "max": 10
          },
          "label": {
            "zh": "depth",
            "en": "Depth"
          }
        }
      ],
      "prerequisites": [
        {
          "id": "tree",
          "type": "binary",
          "required": true,
          "check": "binary:tree"
        }
      ]
    },
    {
      "id": "tree-linux",
      "name": {
        "zh": "目录树结构",
        "en": "Show Directory Tree"
      },
      "tags": [
        "文件",
        "file",
        "树",
        "tree",
        "目录",
        "directory"
      ],
      "category": "file",
      "platform": "linux",
      "exec": {
        "program": "tree",
        "args": [
          "-L",
          "{{depth}}",
          "{{path}}"
        ]
      },
      "adminRequired": false,
      "args": [
        {
          "key": "path",
          "type": "path",
          "required": true,
          "default": ".",
          "label": {
            "zh": "path",
            "en": "Path"
          }
        },
        {
          "key": "depth",
          "type": "number",
          "required": true,
          "default": "3",
          "validation": {
            "min": 1,
            "max": 10
          },
          "label": {
            "zh": "depth",
            "en": "Depth"
          }
        }
      ],
      "prerequisites": [
        {
          "id": "tree",
          "type": "binary",
          "required": true,
          "check": "binary:tree"
        }
      ]
    },
    {
      "id": "tree-win",
      "name": {
        "zh": "目录树结构",
        "en": "Show Directory Tree"
      },
      "tags": [
        "文件",
        "file",
        "树",
        "tree",
        "目录",
        "directory"
      ],
      "category": "file",
      "platform": "win",
      "exec": {
        "program": "tree",
        "args": [
          "/F",
          "{{path}}"
        ]
      },
      "adminRequired": false,
      "args": [
        {
          "key": "path",
          "type": "path",
          "required": true,
          "default": ".",
          "label": {
            "zh": "path",
            "en": "Path"
          }
        }
      ]
    },
    {
      "id": "file-size-mac",
      "name": {
        "zh": "查看文件大小",
        "en": "Show File Size"
      },
      "tags": [
        "文件",
        "file",
        "大小",
        "size",
        "查看",
        "show"
      ],
      "category": "file",
      "platform": "mac",
      "exec": {
        "program": "ls",
        "args": [
          "-lh",
          "{{file}}"
        ]
      },
      "adminRequired": false,
      "args": [
        {
          "key": "file",
          "type": "path",
          "required": true,
          "label": {
            "zh": "file",
            "en": "File"
          }
        }
      ]
    },
    {
      "id": "file-size-linux",
      "name": {
        "zh": "查看文件大小",
        "en": "Show File Size"
      },
      "tags": [
        "文件",
        "file",
        "大小",
        "size",
        "查看",
        "show"
      ],
      "category": "file",
      "platform": "linux",
      "exec": {
        "program": "ls",
        "args": [
          "-lh",
          "{{file}}"
        ]
      },
      "adminRequired": false,
      "args": [
        {
          "key": "file",
          "type": "path",
          "required": true,
          "label": {
            "zh": "file",
            "en": "File"
          }
        }
      ]
    },
    {
      "id": "file-count-mac",
      "name": {
        "zh": "统计文件数量",
        "en": "Count Files"
      },
      "tags": [
        "文件",
        "file",
        "count"
      ],
      "category": "file",
      "platform": "mac",
      "script": {
        "runner": "bash",
        "command": "find {{path}} -type f | wc -l"
      },
      "adminRequired": false,
      "args": [
        {
          "key": "path",
          "type": "path",
          "required": true,
          "default": ".",
          "label": {
            "zh": "path",
            "en": "Path"
          }
        }
      ],
      "prerequisites": [
        {
          "id": "bash",
          "type": "shell",
          "required": true,
          "check": "shell:bash"
        }
      ]
    },
    {
      "id": "file-count-linux",
      "name": {
        "zh": "统计文件数量",
        "en": "Count Files"
      },
      "tags": [
        "文件",
        "file",
        "count"
      ],
      "category": "file",
      "platform": "linux",
      "script": {
        "runner": "bash",
        "command": "find {{path}} -type f | wc -l"
      },
      "adminRequired": false,
      "args": [
        {
          "key": "path",
          "type": "path",
          "required": true,
          "default": ".",
          "label": {
            "zh": "path",
            "en": "Path"
          }
        }
      ],
      "prerequisites": [
        {
          "id": "bash",
          "type": "shell",
          "required": true,
          "check": "shell:bash"
        }
      ]
    },
    {
      "id": "file-permissions-mac",
      "name": {
        "zh": "修改文件权限",
        "en": "Change File Permissions"
      },
      "tags": [
        "文件",
        "file",
        "权限",
        "permissions"
      ],
      "category": "file",
      "platform": "mac",
      "exec": {
        "program": "chmod",
        "args": [
          "{{mode}}",
          "{{file}}"
        ]
      },
      "adminRequired": false,
      "args": [
        {
          "key": "mode",
          "type": "text",
          "required": true,
          "label": {
            "zh": "mode",
            "en": "Mode"
          }
        },
        {
          "key": "file",
          "type": "path",
          "required": true,
          "label": {
            "zh": "file",
            "en": "File"
          }
        }
      ]
    },
    {
      "id": "file-permissions-linux",
      "name": {
        "zh": "修改文件权限",
        "en": "Change File Permissions"
      },
      "tags": [
        "文件",
        "file",
        "权限",
        "permissions"
      ],
      "category": "file",
      "platform": "linux",
      "exec": {
        "program": "chmod",
        "args": [
          "{{mode}}",
          "{{file}}"
        ]
      },
      "adminRequired": false,
      "args": [
        {
          "key": "mode",
          "type": "text",
          "required": true,
          "label": {
            "zh": "mode",
            "en": "Mode"
          }
        },
        {
          "key": "file",
          "type": "path",
          "required": true,
          "label": {
            "zh": "file",
            "en": "File"
          }
        }
      ]
    },
    {
      "id": "file-owner-mac",
      "name": {
        "zh": "修改文件所有者",
        "en": "Change File Owner"
      },
      "tags": [
        "文件",
        "file",
        "所有者",
        "owner"
      ],
      "category": "file",
      "platform": "mac",
      "exec": {
        "program": "chown",
        "args": [
          "{{owner}}",
          "{{file}}"
        ]
      },
      "adminRequired": false,
      "args": [
        {
          "key": "owner",
          "type": "text",
          "required": true,
          "label": {
            "zh": "owner",
            "en": "Owner"
          }
        },
        {
          "key": "file",
          "type": "path",
          "required": true,
          "label": {
            "zh": "file",
            "en": "File"
          }
        }
      ]
    },
    {
      "id": "file-owner-linux",
      "name": {
        "zh": "修改文件所有者",
        "en": "Change File Owner"
      },
      "tags": [
        "文件",
        "file",
        "所有者",
        "owner"
      ],
      "category": "file",
      "platform": "linux",
      "exec": {
        "program": "chown",
        "args": [
          "{{owner}}",
          "{{file}}"
        ]
      },
      "adminRequired": false,
      "args": [
        {
          "key": "owner",
          "type": "text",
          "required": true,
          "label": {
            "zh": "owner",
            "en": "Owner"
          }
        },
        {
          "key": "file",
          "type": "path",
          "required": true,
          "label": {
            "zh": "file",
            "en": "File"
          }
        }
      ]
    },
    {
      "id": "compress-tar-mac",
      "name": {
        "zh": "打包压缩 (tar.gz)",
        "en": "Create tar.gz Archive"
      },
      "tags": [
        "文件",
        "file",
        "压缩",
        "compress",
        "tar"
      ],
      "category": "file",
      "platform": "mac",
      "exec": {
        "program": "tar",
        "args": [
          "-czf",
          "{{output}}.tar.gz",
          "{{input}}"
        ]
      },
      "adminRequired": false,
      "args": [
        {
          "key": "input",
          "type": "path",
          "required": true,
          "label": {
            "zh": "input",
            "en": "Input"
          }
        },
        {
          "key": "output",
          "type": "text",
          "required": true,
          "label": {
            "zh": "output",
            "en": "Output"
          }
        }
      ]
    },
    {
      "id": "compress-tar-linux",
      "name": {
        "zh": "打包压缩 (tar.gz)",
        "en": "Create tar.gz Archive"
      },
      "tags": [
        "文件",
        "file",
        "压缩",
        "compress",
        "tar"
      ],
      "category": "file",
      "platform": "linux",
      "exec": {
        "program": "tar",
        "args": [
          "-czf",
          "{{output}}.tar.gz",
          "{{input}}"
        ]
      },
      "adminRequired": false,
      "args": [
        {
          "key": "input",
          "type": "path",
          "required": true,
          "label": {
            "zh": "input",
            "en": "Input"
          }
        },
        {
          "key": "output",
          "type": "text",
          "required": true,
          "label": {
            "zh": "output",
            "en": "Output"
          }
        }
      ]
    },
    {
      "id": "extract-tar-mac",
      "name": {
        "zh": "解压 (tar.gz)",
        "en": "Extract tar.gz Archive"
      },
      "tags": [
        "文件",
        "file",
        "解压",
        "extract",
        "tar"
      ],
      "category": "file",
      "platform": "mac",
      "exec": {
        "program": "tar",
        "args": [
          "-xzf",
          "{{file}}"
        ]
      },
      "adminRequired": false,
      "args": [
        {
          "key": "file",
          "type": "path",
          "required": true,
          "label": {
            "zh": "file",
            "en": "File"
          }
        }
      ]
    },
    {
      "id": "extract-tar-linux",
      "name": {
        "zh": "解压 (tar.gz)",
        "en": "Extract tar.gz Archive"
      },
      "tags": [
        "文件",
        "file",
        "解压",
        "extract",
        "tar"
      ],
      "category": "file",
      "platform": "linux",
      "exec": {
        "program": "tar",
        "args": [
          "-xzf",
          "{{file}}"
        ]
      },
      "adminRequired": false,
      "args": [
        {
          "key": "file",
          "type": "path",
          "required": true,
          "label": {
            "zh": "file",
            "en": "File"
          }
        }
      ]
    },
    {
      "id": "compress-zip-mac",
      "name": {
        "zh": "ZIP 压缩",
        "en": "Create ZIP Archive"
      },
      "tags": [
        "文件",
        "file",
        "压缩",
        "compress",
        "zip"
      ],
      "category": "file",
      "platform": "mac",
      "exec": {
        "program": "zip",
        "args": [
          "-r",
          "{{output}}.zip",
          "{{input}}"
        ]
      },
      "adminRequired": false,
      "args": [
        {
          "key": "input",
          "type": "path",
          "required": true,
          "label": {
            "zh": "input",
            "en": "Input"
          }
        },
        {
          "key": "output",
          "type": "text",
          "required": true,
          "label": {
            "zh": "output",
            "en": "Output"
          }
        }
      ],
      "prerequisites": [
        {
          "id": "zip",
          "type": "binary",
          "required": true,
          "check": "binary:zip"
        }
      ]
    },
    {
      "id": "compress-zip-linux",
      "name": {
        "zh": "ZIP 压缩",
        "en": "Create ZIP Archive"
      },
      "tags": [
        "文件",
        "file",
        "压缩",
        "compress",
        "zip"
      ],
      "category": "file",
      "platform": "linux",
      "exec": {
        "program": "zip",
        "args": [
          "-r",
          "{{output}}.zip",
          "{{input}}"
        ]
      },
      "adminRequired": false,
      "args": [
        {
          "key": "input",
          "type": "path",
          "required": true,
          "label": {
            "zh": "input",
            "en": "Input"
          }
        },
        {
          "key": "output",
          "type": "text",
          "required": true,
          "label": {
            "zh": "output",
            "en": "Output"
          }
        }
      ],
      "prerequisites": [
        {
          "id": "zip",
          "type": "binary",
          "required": true,
          "check": "binary:zip"
        }
      ]
    },
    {
      "id": "extract-zip-mac",
      "name": {
        "zh": "ZIP 解压",
        "en": "Extract ZIP Archive"
      },
      "tags": [
        "文件",
        "file",
        "解压",
        "extract",
        "zip"
      ],
      "category": "file",
      "platform": "mac",
      "exec": {
        "program": "unzip",
        "args": [
          "{{file}}",
          "-d",
          "{{dest}}"
        ]
      },
      "adminRequired": false,
      "args": [
        {
          "key": "file",
          "type": "path",
          "required": true,
          "label": {
            "zh": "file",
            "en": "File"
          }
        },
        {
          "key": "dest",
          "type": "path",
          "required": true,
          "default": ".",
          "label": {
            "zh": "dest",
            "en": "Destination"
          }
        }
      ],
      "prerequisites": [
        {
          "id": "unzip",
          "type": "binary",
          "required": true,
          "check": "binary:unzip"
        }
      ]
    },
    {
      "id": "extract-zip-linux",
      "name": {
        "zh": "ZIP 解压",
        "en": "Extract ZIP Archive"
      },
      "tags": [
        "文件",
        "file",
        "解压",
        "extract",
        "zip"
      ],
      "category": "file",
      "platform": "linux",
      "exec": {
        "program": "unzip",
        "args": [
          "{{file}}",
          "-d",
          "{{dest}}"
        ]
      },
      "adminRequired": false,
      "args": [
        {
          "key": "file",
          "type": "path",
          "required": true,
          "label": {
            "zh": "file",
            "en": "File"
          }
        },
        {
          "key": "dest",
          "type": "path",
          "required": true,
          "default": ".",
          "label": {
            "zh": "dest",
            "en": "Destination"
          }
        }
      ],
      "prerequisites": [
        {
          "id": "unzip",
          "type": "binary",
          "required": true,
          "check": "binary:unzip"
        }
      ]
    },
    {
      "id": "compress-zip-win",
      "name": {
        "zh": "ZIP 压缩",
        "en": "Create ZIP Archive"
      },
      "tags": [
        "文件",
        "file",
        "压缩",
        "compress",
        "zip"
      ],
      "category": "file",
      "platform": "win",
      "script": {
        "runner": "powershell",
        "command": "Compress-Archive -Path \"{{input}}\" -DestinationPath \"{{output}}.zip\" -Force"
      },
      "adminRequired": false,
      "args": [
        {
          "key": "input",
          "type": "path",
          "required": true,
          "label": {
            "zh": "input",
            "en": "Input"
          }
        },
        {
          "key": "output",
          "type": "text",
          "required": true,
          "label": {
            "zh": "output",
            "en": "Output"
          }
        }
      ],
      "prerequisites": [
        {
          "id": "powershell",
          "type": "shell",
          "required": true,
          "check": "shell:powershell"
        }
      ]
    },
    {
      "id": "extract-zip-win",
      "name": {
        "zh": "ZIP 解压",
        "en": "Extract ZIP Archive"
      },
      "tags": [
        "文件",
        "file",
        "解压",
        "extract",
        "zip"
      ],
      "category": "file",
      "platform": "win",
      "script": {
        "runner": "powershell",
        "command": "Expand-Archive -Path \"{{file}}\" -DestinationPath \"{{dest}}\" -Force"
      },
      "adminRequired": false,
      "args": [
        {
          "key": "file",
          "type": "path",
          "required": true,
          "label": {
            "zh": "file",
            "en": "File"
          }
        },
        {
          "key": "dest",
          "type": "path",
          "required": true,
          "default": ".",
          "label": {
            "zh": "dest",
            "en": "Destination"
          }
        }
      ],
      "prerequisites": [
        {
          "id": "powershell",
          "type": "shell",
          "required": true,
          "check": "shell:powershell"
        }
      ]
    },
    {
      "id": "watch-file-mac",
      "name": {
        "zh": "监听文件变化",
        "en": "Watch File Changes"
      },
      "tags": [
        "文件",
        "file",
        "监听",
        "watch"
      ],
      "category": "file",
      "platform": "mac",
      "exec": {
        "program": "fswatch",
        "args": [
          "{{path}}"
        ]
      },
      "adminRequired": false,
      "args": [
        {
          "key": "path",
          "type": "path",
          "required": true,
          "label": {
            "zh": "path",
            "en": "Path"
          }
        }
      ],
      "prerequisites": [
        {
          "id": "fswatch",
          "type": "binary",
          "required": true,
          "check": "binary:fswatch"
        }
      ]
    },
    {
      "id": "watch-file-linux",
      "name": {
        "zh": "监听文件变化",
        "en": "Watch File Changes"
      },
      "tags": [
        "文件",
        "file",
        "监听",
        "watch"
      ],
      "category": "file",
      "platform": "linux",
      "exec": {
        "program": "fswatch",
        "args": [
          "{{path}}"
        ]
      },
      "adminRequired": false,
      "args": [
        {
          "key": "path",
          "type": "path",
          "required": true,
          "label": {
            "zh": "path",
            "en": "Path"
          }
        }
      ],
      "prerequisites": [
        {
          "id": "fswatch",
          "type": "binary",
          "required": true,
          "check": "binary:fswatch"
        }
      ]
    },
    {
      "id": "tail-log-mac",
      "name": {
        "zh": "实时查看日志",
        "en": "Tail Log File"
      },
      "tags": [
        "文件",
        "file",
        "tail",
        "日志",
        "log",
        "查看",
        "show"
      ],
      "category": "file",
      "platform": "mac",
      "exec": {
        "program": "tail",
        "args": [
          "-f",
          "{{file}}"
        ]
      },
      "adminRequired": false,
      "args": [
        {
          "key": "file",
          "type": "path",
          "required": true,
          "label": {
            "zh": "file",
            "en": "File"
          }
        }
      ]
    },
    {
      "id": "tail-log-linux",
      "name": {
        "zh": "实时查看日志",
        "en": "Tail Log File"
      },
      "tags": [
        "文件",
        "file",
        "tail",
        "日志",
        "log",
        "查看",
        "show"
      ],
      "category": "file",
      "platform": "linux",
      "exec": {
        "program": "tail",
        "args": [
          "-f",
          "{{file}}"
        ]
      },
      "adminRequired": false,
      "args": [
        {
          "key": "file",
          "type": "path",
          "required": true,
          "label": {
            "zh": "file",
            "en": "File"
          }
        }
      ]
    },
    {
      "id": "tail-log-win",
      "name": {
        "zh": "实时查看日志",
        "en": "Tail Log File"
      },
      "tags": [
        "文件",
        "file",
        "tail",
        "日志",
        "log",
        "查看",
        "show"
      ],
      "category": "file",
      "platform": "win",
      "script": {
        "runner": "powershell",
        "command": "Get-Content -Path \"{{file}}\" -Tail {{lines}} -Wait"
      },
      "adminRequired": false,
      "args": [
        {
          "key": "file",
          "type": "path",
          "required": true,
          "label": {
            "zh": "file",
            "en": "File"
          }
        },
        {
          "key": "lines",
          "type": "number",
          "required": true,
          "default": "100",
          "validation": {
            "min": 1,
            "max": 10000
          },
          "label": {
            "zh": "lines",
            "en": "Lines"
          }
        }
      ],
      "prerequisites": [
        {
          "id": "powershell",
          "type": "shell",
          "required": true,
          "check": "shell:powershell"
        }
      ]
    },
    {
      "id": "head-file-mac",
      "name": {
        "zh": "查看文件前 N 行",
        "en": "Show First N Lines"
      },
      "tags": [
        "文件",
        "file",
        "head",
        "查看",
        "show"
      ],
      "category": "file",
      "platform": "mac",
      "exec": {
        "program": "head",
        "args": [
          "-n",
          "{{lines}}",
          "{{file}}"
        ]
      },
      "adminRequired": false,
      "args": [
        {
          "key": "file",
          "type": "path",
          "required": true,
          "label": {
            "zh": "file",
            "en": "File"
          }
        },
        {
          "key": "lines",
          "type": "number",
          "required": true,
          "default": "20",
          "validation": {
            "min": 1,
            "max": 10000
          },
          "label": {
            "zh": "lines",
            "en": "Lines"
          }
        }
      ]
    },
    {
      "id": "head-file-linux",
      "name": {
        "zh": "查看文件前 N 行",
        "en": "Show First N Lines"
      },
      "tags": [
        "文件",
        "file",
        "head",
        "查看",
        "show"
      ],
      "category": "file",
      "platform": "linux",
      "exec": {
        "program": "head",
        "args": [
          "-n",
          "{{lines}}",
          "{{file}}"
        ]
      },
      "adminRequired": false,
      "args": [
        {
          "key": "file",
          "type": "path",
          "required": true,
          "label": {
            "zh": "file",
            "en": "File"
          }
        },
        {
          "key": "lines",
          "type": "number",
          "required": true,
          "default": "20",
          "validation": {
            "min": 1,
            "max": 10000
          },
          "label": {
            "zh": "lines",
            "en": "Lines"
          }
        }
      ]
    },
    {
      "id": "head-file-win",
      "name": {
        "zh": "查看文件前 N 行",
        "en": "Show First N Lines"
      },
      "tags": [
        "文件",
        "file",
        "head",
        "查看",
        "show"
      ],
      "category": "file",
      "platform": "win",
      "script": {
        "runner": "powershell",
        "command": "Get-Content -Path \"{{file}}\" -TotalCount {{lines}}"
      },
      "adminRequired": false,
      "args": [
        {
          "key": "file",
          "type": "path",
          "required": true,
          "label": {
            "zh": "file",
            "en": "File"
          }
        },
        {
          "key": "lines",
          "type": "number",
          "required": true,
          "default": "20",
          "validation": {
            "min": 1,
            "max": 10000
          },
          "label": {
            "zh": "lines",
            "en": "Lines"
          }
        }
      ],
      "prerequisites": [
        {
          "id": "powershell",
          "type": "shell",
          "required": true,
          "check": "shell:powershell"
        }
      ]
    },
    {
      "id": "wc-lines-mac",
      "name": {
        "zh": "统计文件行数",
        "en": "Count File Lines"
      },
      "tags": [
        "文件",
        "file",
        "行数",
        "wc",
        "行",
        "lines"
      ],
      "category": "file",
      "platform": "mac",
      "exec": {
        "program": "wc",
        "args": [
          "-l",
          "{{file}}"
        ]
      },
      "adminRequired": false,
      "args": [
        {
          "key": "file",
          "type": "path",
          "required": true,
          "label": {
            "zh": "file",
            "en": "File"
          }
        }
      ]
    },
    {
      "id": "wc-lines-linux",
      "name": {
        "zh": "统计文件行数",
        "en": "Count File Lines"
      },
      "tags": [
        "文件",
        "file",
        "行数",
        "wc",
        "行",
        "lines"
      ],
      "category": "file",
      "platform": "linux",
      "exec": {
        "program": "wc",
        "args": [
          "-l",
          "{{file}}"
        ]
      },
      "adminRequired": false,
      "args": [
        {
          "key": "file",
          "type": "path",
          "required": true,
          "label": {
            "zh": "file",
            "en": "File"
          }
        }
      ]
    },
    {
      "id": "wc-lines-win",
      "name": {
        "zh": "统计文件行数",
        "en": "Count File Lines"
      },
      "tags": [
        "文件",
        "file",
        "行数",
        "wc",
        "行",
        "lines"
      ],
      "category": "file",
      "platform": "win",
      "script": {
        "runner": "powershell",
        "command": "(Get-Content -Path \"{{file}}\" | Measure-Object -Line).Lines"
      },
      "adminRequired": false,
      "args": [
        {
          "key": "file",
          "type": "path",
          "required": true,
          "label": {
            "zh": "file",
            "en": "File"
          }
        }
      ],
      "prerequisites": [
        {
          "id": "powershell",
          "type": "shell",
          "required": true,
          "check": "shell:powershell"
        }
      ]
    }
  ]
}
